{"global":{"updated":1647109141759,"cases":455058295,"todayCases":1695445,"deaths":6057320,"todayDeaths":6002,"recovered":389015244,"todayRecovered":1463256,"active":59985731,"critical":66437,"casesPerOneMillion":58380,"deathsPerOneMillion":777.1,"tests":5944253970,"testsPerOneMillion":753700.2,"population":7886761879,"oneCasePerPeople":0,"oneDeathPerPeople":0,"oneTestPerPeople":0,"activePerOneMillion":7605.88,"recoveredPerOneMillion":49325.09,"criticalPerOneMillion":8.42,"affectedCountries":227,"last_update":"12.03., 18:19"},"germany":{"last_update":"12.03., 00:00","EWZ":83166711,"cases":16994744,"cases7_per_100k":1496,"ObjectId":1,"newCases":237086,"newDeaths":249}}