{"global":{"updated":1611656176795,"cases":100269668,"todayCases":449212,"deaths":2148753,"todayDeaths":9658,"recovered":72284123,"todayRecovered":533021,"active":25836792,"critical":110404,"casesPerOneMillion":12864,"deathsPerOneMillion":275.7,"tests":1397249155,"testsPerOneMillion":179079.27,"population":7802405951,"oneCasePerPeople":0,"oneDeathPerPeople":0,"oneTestPerPeople":0,"activePerOneMillion":3311.39,"recoveredPerOneMillion":9264.34,"criticalPerOneMillion":14.15,"affectedCountries":221,"last_update":"26.01.2021, 10:16 Uhr"},"germany":{"last_update":"26.01.2021, 00:00 Uhr","EWZ":83166711,"cases":2148077,"cases7_per_100k":107.625994732436,"ObjectId":826,"newCases":6408,"newDeaths":903}}