{"global":{"updated":1649315521682,"cases":495035202,"todayCases":1203188,"deaths":6190877,"todayDeaths":3598,"recovered":430707279,"todayRecovered":1262429,"active":58137046,"critical":54801,"casesPerOneMillion":63508,"deathsPerOneMillion":794.2,"tests":6118065068,"testsPerOneMillion":775214.13,"population":7892096937,"oneCasePerPeople":0,"oneDeathPerPeople":0,"oneTestPerPeople":0,"activePerOneMillion":7366.49,"recoveredPerOneMillion":54574.5,"criticalPerOneMillion":6.94,"affectedCountries":228,"last_update":"07.04., 07:12"},"germany":{"last_update":"07.04., 00:00","EWZ":83166711,"cases":22265788,"cases7_per_100k":1251.3,"ObjectId":51,"newCases":201729,"newDeaths":328}}