{"global":{"updated":1613372450570,"cases":109381072,"todayCases":290079,"deaths":2410948,"todayDeaths":6792,"recovered":81615219,"todayRecovered":345981,"active":25354905,"critical":98498,"casesPerOneMillion":14033,"deathsPerOneMillion":309.3,"tests":1535195824,"testsPerOneMillion":196656.07,"population":7806501252,"oneCasePerPeople":0,"oneDeathPerPeople":0,"oneTestPerPeople":0,"activePerOneMillion":3247.92,"recoveredPerOneMillion":10454.78,"criticalPerOneMillion":12.62,"affectedCountries":221,"last_update":"15.02., 07:00"},"germany":{"last_update":"15.02., 00:00","EWZ":83166711,"cases":2338987,"cases7_per_100k":58.9394475392925,"ObjectId":826,"newCases":4426,"newDeaths":116}}