{"global":{"updated":1664908348723,"cases":623711047,"todayCases":180494,"deaths":6551774,"todayDeaths":684,"recovered":603785569,"todayRecovered":452442,"active":13373704,"critical":39317,"casesPerOneMillion":80016,"deathsPerOneMillion":840.5,"tests":6718295090,"testsPerOneMillion":844567.44,"population":7954717173,"oneCasePerPeople":0,"oneDeathPerPeople":0,"oneTestPerPeople":0,"activePerOneMillion":1681.23,"recoveredPerOneMillion":75902.83,"criticalPerOneMillion":4.94,"affectedCountries":230,"last_update":"04.10., 18:32"},"germany":{"last_update":"04.10., 00:00","EWZ":83166711,"cases":33386229,"cases7_per_100k":374,"ObjectId":1,"newCases":0,"newDeaths":0}}