{"global":{"updated":1652587057693,"cases":520821586,"todayCases":402270,"deaths":6287661,"todayDeaths":876,"recovered":475262675,"todayRecovered":306371,"active":39271250,"critical":39125,"casesPerOneMillion":66817,"deathsPerOneMillion":806.6,"tests":6331125606,"testsPerOneMillion":801420.65,"population":7899878348,"oneCasePerPeople":0,"oneDeathPerPeople":0,"oneTestPerPeople":0,"activePerOneMillion":4971.12,"recoveredPerOneMillion":60160.76,"criticalPerOneMillion":4.95,"affectedCountries":228,"last_update":"15.05., 03:57"},"germany":{"last_update":"15.05., 00:00","EWZ":83166711,"cases":25729848,"cases7_per_100k":452.4,"ObjectId":1,"newCases":6151,"newDeaths":7}}