{"global":{"updated":1657477439465,"cases":560200115,"todayCases":487061,"deaths":6372361,"todayDeaths":887,"recovered":533137676,"todayRecovered":435967,"active":20690078,"critical":37833,"casesPerOneMillion":71868,"deathsPerOneMillion":817.5,"tests":6495257282,"testsPerOneMillion":854363.67,"population":7602450190,"oneCasePerPeople":0,"oneDeathPerPeople":0,"oneTestPerPeople":0,"activePerOneMillion":2721.5,"recoveredPerOneMillion":70127.09,"criticalPerOneMillion":4.98,"affectedCountries":230,"last_update":"10.07., 18:23"},"germany":{"last_update":"10.07., 00:00","EWZ":83166711,"cases":29022265,"cases7_per_100k":672.9,"ObjectId":1,"newCases":0,"newDeaths":0}}