{"global":{"updated":1646713443263,"cases":447839018,"todayCases":1215297,"deaths":6026906,"todayDeaths":4841,"recovered":381929275,"todayRecovered":1799660,"active":59882837,"critical":70238,"casesPerOneMillion":57454,"deathsPerOneMillion":773.2,"tests":5912791322,"testsPerOneMillion":749788.92,"population":7885941139,"oneCasePerPeople":0,"oneDeathPerPeople":0,"oneTestPerPeople":0,"activePerOneMillion":7593.62,"recoveredPerOneMillion":48431.67,"criticalPerOneMillion":8.91,"affectedCountries":226,"last_update":"08.03., 04:24"},"germany":{"last_update":"08.03., 00:00","EWZ":83166711,"cases":16026216,"cases7_per_100k":1293.6,"ObjectId":1,"newCases":156799,"newDeaths":324}}