{"global":{"updated":1664270901635,"cases":620600501,"todayCases":302313,"deaths":6541529,"todayDeaths":803,"recovered":600814815,"todayRecovered":505577,"active":13244157,"critical":39781,"casesPerOneMillion":79617,"deathsPerOneMillion":839.2,"tests":6704894350,"testsPerOneMillion":843034.77,"population":7953283269,"oneCasePerPeople":0,"oneDeathPerPeople":0,"oneTestPerPeople":0,"activePerOneMillion":1665.24,"recoveredPerOneMillion":75542.99,"criticalPerOneMillion":5,"affectedCountries":230,"last_update":"27.09., 09:28"},"germany":{"last_update":"27.09., 00:00","EWZ":83166711,"cases":33041332,"cases7_per_100k":334.9,"ObjectId":1,"newCases":89282,"newDeaths":118}}