{"global":{"updated":1681705096081,"cases":685663314,"todayCases":41102,"deaths":6842532,"todayDeaths":123,"recovered":658390605,"todayRecovered":54891,"active":20430177,"critical":39533,"casesPerOneMillion":87964,"deathsPerOneMillion":877.8,"tests":6970841921,"testsPerOneMillion":877394.44,"population":7944935131,"oneCasePerPeople":0,"oneDeathPerPeople":0,"oneTestPerPeople":0,"activePerOneMillion":2571.47,"recoveredPerOneMillion":82869.22,"criticalPerOneMillion":4.98,"affectedCountries":231,"last_update":"17.04., 04:18"},"germany":{"last_update":"17.04., 00:00","EWZ":83166711,"cases":38382386,"cases7_per_100k":14,"ObjectId":1,"newCases":0,"newDeaths":0}}