{"global":{"updated":1650345679375,"cases":505043725,"todayCases":315841,"deaths":6224496,"todayDeaths":1286,"recovered":456512854,"todayRecovered":995929,"active":42306375,"critical":42014,"casesPerOneMillion":64792,"deathsPerOneMillion":798.5,"tests":6224749287,"testsPerOneMillion":788486.48,"population":7894554232,"oneCasePerPeople":0,"oneDeathPerPeople":0,"oneTestPerPeople":0,"activePerOneMillion":5358.93,"recoveredPerOneMillion":57826.3,"criticalPerOneMillion":5.32,"affectedCountries":228,"last_update":"19.04., 05:21"},"germany":{"last_update":"19.04., 00:00","EWZ":83166711,"cases":23459628,"cases7_per_100k":669.9,"ObjectId":1,"newCases":22483,"newDeaths":7}}