{"lowest5":[{"cases_per_100k":2805.75000935874,"RS":"09662","EWZ":53426,"cases7_per_100k":7.5,"GEN":"Schweinfurt","BEZ":"Kreisfreie Stadt","newCases":-1},{"cases_per_100k":1292.66224080952,"RS":"07320","EWZ":34193,"cases7_per_100k":11.7,"GEN":"Zweibrücken","BEZ":"Kreisfreie Stadt","newCases":null},{"cases_per_100k":2732.70094447242,"RS":"09185","EWZ":97303,"cases7_per_100k":15.4,"GEN":"Neuburg-Schrobenhausen","BEZ":"Landkreis","newCases":3},{"cases_per_100k":1670.50965292601,"RS":"05515","EWZ":315293,"cases7_per_100k":15.9,"GEN":"Münster","BEZ":"Kreisfreie Stadt","newCases":18},{"cases_per_100k":672.591077053984,"RS":"13003","EWZ":209191,"cases7_per_100k":17.2,"GEN":"Rostock","BEZ":"Kreisfreie Stadt","newCases":6}],"highest5":[{"cases_per_100k":5364.62815423479,"RS":"09377","EWZ":72046,"cases7_per_100k":351.2,"GEN":"Tirschenreuth","BEZ":"Landkreis","newCases":41},{"cases_per_100k":4433.28057256899,"RS":"09479","EWZ":72655,"cases7_per_100k":225.7,"GEN":"Wunsiedel i. Fichtelgebirge","BEZ":"Landkreis","newCases":39},{"cases_per_100k":4319.70284030869,"RS":"16066","EWZ":124916,"cases7_per_100k":216.1,"GEN":"Schmalkalden-Meiningen","BEZ":"Landkreis","newCases":46},{"cases_per_100k":4493.18057828696,"RS":"09464","EWZ":45825,"cases7_per_100k":198.6,"GEN":"Hof","BEZ":"Kreisfreie Stadt","newCases":16},{"cases_per_100k":3738.42900555968,"RS":"03460","EWZ":142814,"cases7_per_100k":191.9,"GEN":"Vechta","BEZ":"Landkreis","newCases":49}],"highest5EWZ":[{"cases_per_100k":2635.58916943158,"RS":"02000","EWZ":1847253,"cases7_per_100k":59.7,"GEN":"Hamburg","BEZ":"Kreisfreie Stadt","newCases":228},{"cases_per_100k":3555.9274665718,"RS":"09162","EWZ":1484226,"cases7_per_100k":38.4,"GEN":"München","BEZ":"Kreisfreie Stadt","newCases":83},{"cases_per_100k":2472.78792514141,"RS":"03241","EWZ":1157115,"cases7_per_100k":90.1,"GEN":"Region Hannover","BEZ":"Landkreis","newCases":151},{"cases_per_100k":2956.80614194986,"RS":"05315","EWZ":1087863,"cases7_per_100k":67.7,"GEN":"Köln","BEZ":"Kreisfreie Stadt","newCases":116},{"cases_per_100k":3309.23000340591,"RS":"06412","EWZ":763380,"cases7_per_100k":57.1,"GEN":"Frankfurt am Main","BEZ":"Kreisfreie Stadt","newCases":70}],"highest5casesPer100k":[{"cases_per_100k":6252.04331494072,"RS":"14625","EWZ":299758,"cases7_per_100k":72.4,"GEN":"Bautzen","BEZ":"Landkreis","newCases":48},{"cases_per_100k":5995.85607318151,"RS":"14521","EWZ":334948,"cases7_per_100k":61.5,"GEN":"Erzgebirgskreis","BEZ":"Landkreis","newCases":24},{"cases_per_100k":5886.73621460507,"RS":"14628","EWZ":245586,"cases7_per_100k":95.7,"GEN":"Sächsische Schweiz-Osterzgebirge","BEZ":"Landkreis","newCases":48},{"cases_per_100k":5735.87891977446,"RS":"14626","EWZ":252725,"cases7_per_100k":73.6,"GEN":"Görlitz","BEZ":"Landkreis","newCases":30},{"cases_per_100k":5604.69642546323,"RS":"16069","EWZ":63197,"cases7_per_100k":185.1,"GEN":"Hildburghausen","BEZ":"Landkreis","newCases":11}]}