{"data":[{"betten_frei":7,"betten_belegt":72,"betten_gesamt":79,"Anteil_betten_frei":8.86075949367089,"faelle_covid_aktuell":1,"faelle_covid_aktuell_beatmet":0,"Anteil_covid_beatmet":0,"Anteil_COVID_betten":1.639344,"daten_stand":"07.06.2022 10:19 Uhr","OBJECTID":154,"ADE":4,"GF":4,"BSG":1,"RS":"07211","AGS":"07211","SDV_RS":"072110000000","GEN":"Trier","BEZ":"Kreisfreie Stadt","IBZ":40,"BEM":"--","NBD":"ja","SN_L":"07","SN_R":"2","SN_K":"11","SN_V1":"00","SN_V2":"00","SN_G":"000","FK_S3":"K","NUTS":"DEB21","RS_0":"072110000000","AGS_0":"07211000","WSK":"2017/07/01 00:00:00.000","EWZ":110674,"KFL":117.06,"DEBKG_ID":"DEBKGDL20000E6QK","Shape__Area":115582625.036499,"Shape__Length":86468.3940709615,"death_rate":0.205107168495539,"cases":29253,"deaths":60,"cases_per_100k":26431.682237924,"cases_per_population":26.431682237924,"BL":"Rheinland-Pfalz","BL_ID":"7","county":"SK Trier","last_update":"08.06., 00:00","cases7_per_100k":234.924191770425,"recovered":null,"EWZ_BL":4098391,"cases7_bl_per_100k":225.722728748916,"cases7_bl":9251,"death7_bl":0,"cases7_lk":260,"death7_lk":0,"cases7_per_100k_txt":"234,9","AdmUnitId":7211}]}