{"data":[{"betten_frei":15,"betten_belegt":59,"betten_gesamt":74,"Anteil_betten_frei":20.2702702702703,"faelle_covid_aktuell":11,"faelle_covid_aktuell_beatmet":4,"Anteil_covid_beatmet":36,"Anteil_COVID_betten":18.64407,"daten_stand":"15.01.2021 12:15 Uhr","OBJECTID":191,"ADE":4,"GF":4,"BSG":1,"RS":"08136","AGS":"08136","SDV_RS":"081365001088","GEN":"Ostalbkreis","BEZ":"Landkreis","IBZ":43,"BEM":"--","NBD":"nein","SN_L":"08","SN_R":"1","SN_K":"36","SN_V1":"00","SN_V2":"00","SN_G":"000","FK_S3":"R","NUTS":"DE11D","RS_0":"081360000000","AGS_0":"08136000","WSK":"2009/01/01 00:00:00.000","EWZ":314025,"KFL":1511.38,"DEBKG_ID":"DEBKGDL20000E1I0","Shape__Area":1509494065.33569,"Shape__Length":347555.316527476,"death_rate":1.90545987541224,"cases":8187,"deaths":156,"cases_per_100k":2607.11726773346,"cases_per_population":2.60711726773346,"BL":"Baden-Württemberg","BL_ID":"8","county":"LK Ostalbkreis","last_update":"16.01.2021, 00:00 Uhr","cases7_per_100k":184.061778520818,"recovered":null,"EWZ_BL":11100394,"cases7_bl_per_100k":123.103738479913,"cases7_bl":13665,"death7_bl":40,"cases7_lk":578,"death7_lk":0,"cases7_per_100k_txt":"184,1"}]}