{"data":[{"betten_frei":7,"betten_belegt":46,"betten_gesamt":53,"Anteil_betten_frei":13.2075471698113,"faelle_covid_aktuell":1,"faelle_covid_aktuell_beatmet":1,"Anteil_covid_beatmet":100,"Anteil_COVID_betten":2.857143,"daten_stand":"18.05.2022 10:19 Uhr","OBJECTID":200,"ADE":4,"GF":4,"BSG":1,"RS":"08231","AGS":"08231","SDV_RS":"082310000000","GEN":"Pforzheim","BEZ":"Stadtkreis","IBZ":41,"BEM":"--","NBD":"ja","SN_L":"08","SN_R":"2","SN_K":"31","SN_V1":"00","SN_V2":"00","SN_G":"000","FK_S3":"R","NUTS":"DE129","RS_0":"082310000000","AGS_0":"08231000","WSK":"1975/09/20 00:00:00.000","EWZ":126016,"KFL":97.99,"DEBKG_ID":"DEBKGDL20000E3GL","Shape__Area":98121999.5908203,"Shape__Length":57899.0333914585,"death_rate":0.732451678535097,"cases":44235,"deaths":324,"cases_per_100k":35102.6853732859,"cases_per_population":35.1026853732859,"BL":"Baden-Württemberg","BL_ID":"8","county":"SK Pforzheim","last_update":"19.05., 00:00","cases7_per_100k":264.252158456069,"recovered":null,"EWZ_BL":11103043,"cases7_bl_per_100k":356.541895766773,"cases7_bl":39587,"death7_bl":7,"cases7_lk":333,"death7_lk":0,"cases7_per_100k_txt":"264,3","AdmUnitId":8231}]}