{"data":[{"betten_frei":6,"betten_belegt":46,"betten_gesamt":52,"Anteil_betten_frei":11.5384615384615,"faelle_covid_aktuell":1,"faelle_covid_aktuell_beatmet":1,"Anteil_covid_beatmet":100,"Anteil_COVID_betten":3.125,"daten_stand":"16.09.2022 10:21 Uhr","OBJECTID":246,"ADE":4,"GF":4,"BSG":1,"RS":"09261","AGS":"09261","SDV_RS":"092610000000","GEN":"Landshut","BEZ":"Kreisfreie Stadt","IBZ":40,"BEM":"--","NBD":"ja","SN_L":"09","SN_R":"2","SN_K":"61","SN_V1":"00","SN_V2":"00","SN_G":"000","FK_S3":"R","NUTS":"DE221","RS_0":"092610000000","AGS_0":"09261000","WSK":"1974/07/01 00:00:00.000","EWZ":73065,"KFL":65.83,"DEBKG_ID":"DEBKGDL20000E5OT","Shape__Area":66198281.5153809,"Shape__Length":67302.8073367567,"death_rate":0.603113454798068,"cases":31669,"deaths":191,"cases_per_100k":43343.5981660166,"cases_per_population":43.3435981660166,"BL":"Bayern","BL_ID":"9","county":"SK Landshut","last_update":"17.09., 00:00","cases7_per_100k":244.987340039691,"recovered":null,"EWZ_BL":13140183,"cases7_bl_per_100k":284.980810389018,"cases7_bl":37447,"death7_bl":12,"cases7_lk":179,"death7_lk":0,"cases7_per_100k_txt":"245,0","AdmUnitId":9261}]}