{"data":[{"betten_frei":5,"betten_belegt":43,"betten_gesamt":48,"Anteil_betten_frei":10.4166666666667,"faelle_covid_aktuell":1,"faelle_covid_aktuell_beatmet":1,"Anteil_covid_beatmet":100,"Anteil_COVID_betten":2.325581,"daten_stand":"08.10.2021 12:15 Uhr","OBJECTID":312,"ADE":4,"GF":4,"BSG":1,"RS":"09774","AGS":"09774","SDV_RS":"097740135135","GEN":"Günzburg","BEZ":"Landkreis","IBZ":43,"BEM":"--","NBD":"ja","SN_L":"09","SN_R":"7","SN_K":"74","SN_V1":"00","SN_V2":"00","SN_G":"000","FK_S3":"R","NUTS":"DE278","RS_0":"097740000000","AGS_0":"09774000","WSK":"2016/07/01 00:00:00.000","EWZ":127342,"KFL":762.43,"DEBKG_ID":"DEBKGDL20000E5OH","Shape__Area":763092354.290771,"Shape__Length":231983.896909515,"death_rate":1.43784196462654,"cases":7859,"deaths":113,"cases_per_100k":6171.56947432897,"cases_per_population":6.17156947432897,"BL":"Bayern","BL_ID":"9","county":"LK Günzburg","last_update":"09.10., 00:00","cases7_per_100k":66.7493835498107,"recovered":null,"EWZ_BL":13140183,"cases7_bl_per_100k":89.9074236637344,"cases7_bl":11814,"death7_bl":16,"cases7_lk":85,"death7_lk":0,"cases7_per_100k_txt":"66,7","AdmUnitId":9774}]}