{"data":[{"betten_frei":1,"betten_belegt":22,"betten_gesamt":23,"Anteil_betten_frei":4.34782608695652,"faelle_covid_aktuell":1,"faelle_covid_aktuell_beatmet":0,"Anteil_covid_beatmet":0,"Anteil_COVID_betten":4.545455,"daten_stand":"15.03.2023 11:20 Uhr","OBJECTID":4,"ADE":4,"GF":4,"BSG":1,"RS":"01004","AGS":"01004","SDV_RS":"010040000000","GEN":"Neumünster","BEZ":"Kreisfreie Stadt","IBZ":40,"BEM":"--","NBD":"ja","SN_L":"01","SN_R":"0","SN_K":"04","SN_V1":"00","SN_V2":"00","SN_G":"000","FK_S3":"R","NUTS":"DEF04","RS_0":"010040000000","AGS_0":"01004000","WSK":"1970/04/26 00:00:00.000","EWZ":79496,"KFL":71.66,"DEBKG_ID":"DEBKGDL20000E4KX","Shape__Area":71402241.6633301,"Shape__Length":54863.9954163623,"death_rate":0.412135814602289,"cases":31543,"deaths":130,"cases_per_100k":39678.7259736339,"cases_per_population":39.6787259736339,"BL":"Schleswig-Holstein","BL_ID":"1","county":"SK Neumünster","last_update":"16.03., 00:00","cases7_per_100k":30.1901982489685,"recovered":null,"EWZ_BL":2922005,"cases7_bl_per_100k":33.2648301423167,"cases7_bl":972,"death7_bl":4,"cases7_lk":24,"death7_lk":1,"cases7_per_100k_txt":"30,2","AdmUnitId":1004}]}