{"data":[{"betten_frei":13,"betten_belegt":29,"betten_gesamt":42,"Anteil_betten_frei":30.952380952381,"faelle_covid_aktuell":0,"faelle_covid_aktuell_beatmet":0,"Anteil_covid_beatmet":0,"Anteil_COVID_betten":0,"daten_stand":"06.11.2021 12:15 Uhr","OBJECTID":11,"ADE":4,"GF":4,"BSG":1,"RS":"01058","AGS":"01058","SDV_RS":"010580135135","GEN":"Rendsburg-Eckernförde","BEZ":"Kreis","IBZ":42,"BEM":"--","NBD":"ja","SN_L":"01","SN_R":"0","SN_K":"58","SN_V1":"00","SN_V2":"00","SN_G":"000","FK_S3":"R","NUTS":"DEF0B","RS_0":"010580000000","AGS_0":"01058000","WSK":"2014/02/01 00:00:00.000","EWZ":274765,"KFL":2189.78,"DEBKG_ID":"DEBKGDL20000E5OD","Shape__Area":2167736469.53174,"Shape__Length":371442.746317188,"death_rate":1.19586881681464,"cases":5519,"deaths":66,"cases_per_100k":2008.62555274507,"cases_per_population":2.00862555274507,"BL":"Schleswig-Holstein","BL_ID":"1","county":"LK Rendsburg-Eckernförde","last_update":"07.11., 00:00","cases7_per_100k":59.6873692064128,"recovered":null,"EWZ_BL":2910875,"cases7_bl_per_100k":75.1320479237343,"cases7_bl":2187,"death7_bl":0,"cases7_lk":164,"death7_lk":0,"cases7_per_100k_txt":"59,7","AdmUnitId":1058}]}