{"data":[{"betten_frei":0,"betten_belegt":24,"betten_gesamt":24,"Anteil_betten_frei":0,"faelle_covid_aktuell":0,"faelle_covid_aktuell_beatmet":0,"Anteil_covid_beatmet":0,"Anteil_COVID_betten":0,"daten_stand":"23.01.2023 11:21 Uhr","OBJECTID":33,"ADE":4,"GF":4,"BSG":1,"RS":"03257","AGS":"03257","SDV_RS":"032570035035","GEN":"Schaumburg","BEZ":"Landkreis","IBZ":43,"BEM":"--","NBD":"ja","SN_L":"03","SN_R":"2","SN_K":"57","SN_V1":"00","SN_V2":"00","SN_G":"000","FK_S3":"K","NUTS":"DE928","RS_0":"032570000000","AGS_0":"03257000","WSK":"2009/01/01 00:00:00.000","EWZ":158108,"KFL":675.66,"DEBKG_ID":"DEBKGDL20000E2WJ","Shape__Area":675778190.708496,"Shape__Length":205685.418205366,"death_rate":0.36350186214989,"cases":78404,"deaths":285,"cases_per_100k":49588.8886077871,"cases_per_population":49.5888886077871,"BL":"Niedersachsen","BL_ID":"3","county":"LK Schaumburg","last_update":"24.01., 00:00","cases7_per_100k":117.641106079389,"recovered":null,"EWZ_BL":8027031,"cases7_bl_per_100k":107.611394549242,"cases7_bl":8638,"death7_bl":7,"cases7_lk":186,"death7_lk":0,"cases7_per_100k_txt":"117,6","AdmUnitId":3257}]}