{"data":[{"betten_frei":5,"betten_belegt":7,"betten_gesamt":12,"Anteil_betten_frei":41.6666666666667,"faelle_covid_aktuell":0,"faelle_covid_aktuell_beatmet":0,"Anteil_covid_beatmet":0,"Anteil_COVID_betten":0,"daten_stand":"14.05.2022 10:19 Uhr","OBJECTID":35,"ADE":4,"GF":4,"BSG":1,"RS":"03352","AGS":"03352","SDV_RS":"033520011011","GEN":"Cuxhaven","BEZ":"Landkreis","IBZ":43,"BEM":"--","NBD":"ja","SN_L":"03","SN_R":"3","SN_K":"52","SN_V1":"00","SN_V2":"00","SN_G":"000","FK_S3":"K","NUTS":"DE932","RS_0":"033520000000","AGS_0":"03352000","WSK":"2010/01/01 00:00:00.000","EWZ":198826,"KFL":2058.96,"DEBKG_ID":"DEBKGDL20000E0P8","Shape__Area":2057837437.46387,"Shape__Length":308901.909988568,"death_rate":0.438222070457003,"cases":52713,"deaths":231,"cases_per_100k":26512.1261806806,"cases_per_population":26.5121261806806,"BL":"Niedersachsen","BL_ID":"3","county":"LK Cuxhaven","last_update":"15.05., 00:00","cases7_per_100k":757.446209248287,"recovered":null,"EWZ_BL":8003421,"cases7_bl_per_100k":612.900408462831,"cases7_bl":49053,"death7_bl":8,"cases7_lk":1506,"death7_lk":0,"cases7_per_100k_txt":"757,4","AdmUnitId":3352}]}