{"data":[{"betten_frei":11,"betten_belegt":70,"betten_gesamt":81,"Anteil_betten_frei":13.5802469135802,"faelle_covid_aktuell":6,"faelle_covid_aktuell_beatmet":3,"Anteil_covid_beatmet":50,"Anteil_COVID_betten":9.836065,"daten_stand":"04.11.2022 11:20 Uhr","OBJECTID":67,"ADE":4,"GF":4,"BSG":1,"RS":"05114","AGS":"05114","SDV_RS":"051140000000","GEN":"Krefeld","BEZ":"Kreisfreie Stadt","IBZ":40,"BEM":"--","NBD":"ja","SN_L":"05","SN_R":"1","SN_K":"14","SN_V1":"00","SN_V2":"00","SN_G":"000","FK_S3":"R","NUTS":"DEA14","RS_0":"051140000000","AGS_0":"05114000","WSK":"2001/02/01 00:00:00.000","EWZ":227050,"KFL":137.77,"DEBKG_ID":"DEBKGDL20000DW8W","Shape__Area":136653261.214478,"Shape__Length":63471.9914602398,"death_rate":0.340638260768471,"cases":86015,"deaths":293,"cases_per_100k":37883.7260515305,"cases_per_population":37.8837260515305,"BL":"Nordrhein-Westfalen","BL_ID":"5","county":"SK Krefeld","last_update":"04.11., 00:00","cases7_per_100k":332.525875357851,"recovered":null,"EWZ_BL":17924591,"cases7_bl_per_100k":362.128206997861,"cases7_bl":64910,"death7_bl":14,"cases7_lk":755,"death7_lk":0,"cases7_per_100k_txt":"332,5","AdmUnitId":5114}]}