{"data":[{"betten_frei":13,"betten_belegt":277,"betten_gesamt":290,"Anteil_betten_frei":4.48275862068965,"faelle_covid_aktuell":9,"faelle_covid_aktuell_beatmet":7,"Anteil_covid_beatmet":77,"Anteil_COVID_betten":3.249098,"daten_stand":"29.06.2021 12:15 Uhr","OBJECTID":79,"ADE":4,"GF":4,"BSG":1,"RS":"05314","AGS":"05314","SDV_RS":"053140000000","GEN":"Bonn","BEZ":"Kreisfreie Stadt","IBZ":40,"BEM":"--","NBD":"ja","SN_L":"05","SN_R":"3","SN_K":"14","SN_V1":"00","SN_V2":"00","SN_G":"000","FK_S3":"R","NUTS":"DEA22","RS_0":"053140000000","AGS_0":"05314000","WSK":"1969/08/01 00:00:00.000","EWZ":329673,"KFL":141.06,"DEBKG_ID":"DEBKGDL20000E68K","Shape__Area":141581438.620239,"Shape__Length":65347.5203943689,"death_rate":1.71915830009627,"cases":14542,"deaths":250,"cases_per_100k":4411.03760392874,"cases_per_population":4.41103760392874,"BL":"Nordrhein-Westfalen","BL_ID":"5","county":"SK Bonn","last_update":"29.06., 00:00","cases7_per_100k":4.85329402165176,"recovered":null,"EWZ_BL":17947221,"cases7_bl_per_100k":5.57746516856287,"cases7_bl":1001,"death7_bl":1,"cases7_lk":16,"death7_lk":0,"cases7_per_100k_txt":"4,9","AdmUnitId":5314}]}