{"data":[{"betten_frei":3,"betten_belegt":32,"betten_gesamt":35,"Anteil_betten_frei":8.57142857142857,"faelle_covid_aktuell":1,"faelle_covid_aktuell_beatmet":1,"Anteil_covid_beatmet":100,"Anteil_COVID_betten":3.125,"daten_stand":"04.02.2023 11:21 Uhr","OBJECTID":86,"ADE":4,"GF":4,"BSG":1,"RS":"05370","AGS":"05370","SDV_RS":"053700016016","GEN":"Heinsberg","BEZ":"Kreis","IBZ":42,"BEM":"--","NBD":"ja","SN_L":"05","SN_R":"3","SN_K":"70","SN_V1":"00","SN_V2":"00","SN_G":"000","FK_S3":"R","NUTS":"DEA29","RS_0":"053700000000","AGS_0":"05370000","WSK":"2009/01/01 00:00:00.000","EWZ":258306,"KFL":627.92,"DEBKG_ID":"DEBKGDL20000DX0T","Shape__Area":627310851.182861,"Shape__Length":166217.280069434,"death_rate":0.63348507432623,"cases":99292,"deaths":629,"cases_per_100k":38439.6800693751,"cases_per_population":38.4396800693751,"BL":"Nordrhein-Westfalen","BL_ID":"5","county":"LK Heinsberg","last_update":"04.02., 00:00","cases7_per_100k":144.015237741284,"recovered":null,"EWZ_BL":17924591,"cases7_bl_per_100k":120.928840161541,"cases7_bl":21676,"death7_bl":8,"cases7_lk":372,"death7_lk":0,"cases7_per_100k_txt":"144,0","AdmUnitId":5370}]}