{"data":[{"betten_frei":22,"betten_belegt":107,"betten_gesamt":129,"Anteil_betten_frei":17.0542635658915,"faelle_covid_aktuell":2,"faelle_covid_aktuell_beatmet":0,"Anteil_covid_beatmet":0,"Anteil_COVID_betten":2.247191,"daten_stand":"14.02.2023 11:20 Uhr","OBJECTID":98,"ADE":4,"GF":4,"BSG":1,"RS":"05711","AGS":"05711","SDV_RS":"057110000000","GEN":"Bielefeld","BEZ":"Kreisfreie Stadt","IBZ":40,"BEM":"--","NBD":"ja","SN_L":"05","SN_R":"7","SN_K":"11","SN_V1":"00","SN_V2":"00","SN_G":"000","FK_S3":"R","NUTS":"DEA41","RS_0":"057110000000","AGS_0":"05711000","WSK":"1973/01/01 00:00:00.000","EWZ":334002,"KFL":258.83,"DEBKG_ID":"DEBKGDL20000E4DX","Shape__Area":258894396.253174,"Shape__Length":97937.5188481441,"death_rate":0.44685072219235,"cases":161799,"deaths":723,"cases_per_100k":48442.5242962617,"cases_per_population":48.4425242962617,"BL":"Nordrhein-Westfalen","BL_ID":"5","county":"SK Bielefeld","last_update":"15.02., 00:00","cases7_per_100k":96.1072089388686,"recovered":null,"EWZ_BL":17924591,"cases7_bl_per_100k":121.637363998989,"cases7_bl":21803,"death7_bl":7,"cases7_lk":321,"death7_lk":0,"cases7_per_100k_txt":"96,1","AdmUnitId":5711}]}