{"data":[{"betten_frei":8,"betten_belegt":95,"betten_gesamt":103,"Anteil_betten_frei":7.76699029126214,"faelle_covid_aktuell":5,"faelle_covid_aktuell_beatmet":3,"Anteil_covid_beatmet":60,"Anteil_COVID_betten":5.263158,"daten_stand":"03.12.2021 12:15 Uhr","OBJECTID":160,"ADE":4,"GF":4,"BSG":1,"RS":"07312","AGS":"07312","SDV_RS":"073120000000","GEN":"Kaiserslautern","BEZ":"Kreisfreie Stadt","IBZ":40,"BEM":"--","NBD":"ja","SN_L":"07","SN_R":"3","SN_K":"12","SN_V1":"00","SN_V2":"00","SN_G":"000","FK_S3":"K","NUTS":"DEB32","RS_0":"073120000000","AGS_0":"07312000","WSK":"1969/06/07 00:00:00.000","EWZ":99662,"KFL":139.7,"DEBKG_ID":"DEBKGDL20000DWDZ","Shape__Area":140149191.699829,"Shape__Length":74942.6497413962,"death_rate":2.11640211640212,"cases":5859,"deaths":124,"cases_per_100k":5878.87058256908,"cases_per_population":5.87887058256908,"BL":"Rheinland-Pfalz","BL_ID":"7","county":"SK Kaiserslautern","last_update":"04.12., 00:00","cases7_per_100k":477.614336457225,"recovered":null,"EWZ_BL":4098391,"cases7_bl_per_100k":322.150814795367,"cases7_bl":13203,"death7_bl":12,"cases7_lk":476,"death7_lk":1,"cases7_per_100k_txt":"477,6","AdmUnitId":7312}]}