{"data":[{"betten_frei":2,"betten_belegt":8,"betten_gesamt":10,"Anteil_betten_frei":20,"faelle_covid_aktuell":5,"faelle_covid_aktuell_beatmet":4,"Anteil_covid_beatmet":80,"Anteil_COVID_betten":62.5,"daten_stand":"02.06.2021 12:15 Uhr","OBJECTID":219,"ADE":4,"GF":4,"BSG":1,"RS":"08426","AGS":"08426","SDV_RS":"084265003021","GEN":"Biberach","BEZ":"Landkreis","IBZ":43,"BEM":"--","NBD":"ja","SN_L":"08","SN_R":"4","SN_K":"26","SN_V1":"00","SN_V2":"00","SN_G":"000","FK_S3":"R","NUTS":"DE146","RS_0":"084260000000","AGS_0":"08426000","WSK":"2009/01/01 00:00:00.000","EWZ":201282,"KFL":1409.49,"DEBKG_ID":"DEBKGDL20000E1E7","Shape__Area":1408881133.10425,"Shape__Length":292822.021632747,"death_rate":1.98491004062681,"cases":8615,"deaths":171,"cases_per_100k":4280.06478472988,"cases_per_population":4.28006478472988,"BL":"Baden-Württemberg","BL_ID":"8","county":"LK Biberach","last_update":"02.06., 00:00","cases7_per_100k":55.6433262785545,"recovered":null,"EWZ_BL":11100394,"cases7_bl_per_100k":44.9893940701564,"cases7_bl":4994,"death7_bl":6,"cases7_lk":112,"death7_lk":0,"cases7_per_100k_txt":"55,6","AdmUnitId":8426}]}