{"data":[{"betten_frei":6,"betten_belegt":61,"betten_gesamt":67,"Anteil_betten_frei":8.95522388059701,"faelle_covid_aktuell":3,"faelle_covid_aktuell_beatmet":3,"Anteil_covid_beatmet":100,"Anteil_COVID_betten":4.918033,"daten_stand":"14.06.2022 10:19 Uhr","OBJECTID":242,"ADE":4,"GF":4,"BSG":1,"RS":"09187","AGS":"09187","SDV_RS":"091630000000","GEN":"Rosenheim","BEZ":"Landkreis","IBZ":43,"BEM":"--","NBD":"ja","SN_L":"09","SN_R":"1","SN_K":"87","SN_V1":"00","SN_V2":"00","SN_G":"000","FK_S3":"R","NUTS":"DE21K","RS_0":"091870000000","AGS_0":"09187000","WSK":"2004/12/31 00:00:00.000","EWZ":261721,"KFL":1439.45,"DEBKG_ID":"DEBKGDL20000DZTP","Shape__Area":1441414860.15088,"Shape__Length":378158.132107578,"death_rate":0.643121186478422,"cases":112265,"deaths":722,"cases_per_100k":42894.9148138667,"cases_per_population":42.8949148138667,"BL":"Bayern","BL_ID":"9","county":"LK Rosenheim","last_update":"14.06., 00:00","cases7_per_100k":435.578344878707,"recovered":null,"EWZ_BL":13140183,"cases7_bl_per_100k":425.930141155568,"cases7_bl":55968,"death7_bl":10,"cases7_lk":1140,"death7_lk":0,"cases7_per_100k_txt":"435,6","AdmUnitId":9187}]}