{"data":[{"betten_frei":4,"betten_belegt":49,"betten_gesamt":53,"Anteil_betten_frei":7.54716981132075,"faelle_covid_aktuell":1,"faelle_covid_aktuell_beatmet":0,"Anteil_covid_beatmet":0,"Anteil_COVID_betten":2.777778,"daten_stand":"10.06.2022 10:19 Uhr","OBJECTID":293,"ADE":4,"GF":4,"BSG":1,"RS":"09661","AGS":"09661","SDV_RS":"096610000000","GEN":"Aschaffenburg","BEZ":"Kreisfreie Stadt","IBZ":40,"BEM":"--","NBD":"ja","SN_L":"09","SN_R":"6","SN_K":"61","SN_V1":"00","SN_V2":"00","SN_G":"000","FK_S3":"R","NUTS":"DE261","RS_0":"096610000000","AGS_0":"09661000","WSK":"1978/05/01 00:00:00.000","EWZ":70858,"KFL":62.45,"DEBKG_ID":"DEBKGDL20000E2XA","Shape__Area":61907646.1359863,"Shape__Length":50363.8974170639,"death_rate":0.695263264891238,"cases":24595,"deaths":171,"cases_per_100k":34710.2656016258,"cases_per_population":34.7102656016258,"BL":"Bayern","BL_ID":"9","county":"SK Aschaffenburg","last_update":"10.06., 00:00","cases7_per_100k":282.254650145361,"recovered":null,"EWZ_BL":13140183,"cases7_bl_per_100k":308.519295355323,"cases7_bl":40540,"death7_bl":8,"cases7_lk":200,"death7_lk":1,"cases7_per_100k_txt":"282,3","AdmUnitId":9661}]}