{"data":[{"betten_frei":9,"betten_belegt":8,"betten_gesamt":17,"Anteil_betten_frei":52.9411764705882,"faelle_covid_aktuell":1,"faelle_covid_aktuell_beatmet":1,"Anteil_covid_beatmet":100,"Anteil_COVID_betten":12.5,"daten_stand":"13.02.2023 11:21 Uhr","OBJECTID":349,"ADE":4,"GF":4,"BSG":1,"RS":"13074","AGS":"13074","SDV_RS":"130740087087","GEN":"Nordwestmecklenburg","BEZ":"Landkreis","IBZ":43,"BEM":"--","NBD":"ja","SN_L":"13","SN_R":"0","SN_K":"74","SN_V1":"00","SN_V2":"00","SN_G":"000","FK_S3":"R","NUTS":"DE80M","RS_0":"130740000000","AGS_0":"13074000","WSK":"2011/09/04 00:00:00.000","EWZ":158449,"KFL":2127.05,"DEBKG_ID":"DEBKGDL20000QGFQ","Shape__Area":2124163939.49634,"Shape__Length":423468.448156752,"death_rate":0.25969232391674,"cases":75859,"deaths":197,"cases_per_100k":47875.972710462,"cases_per_population":47.875972710462,"BL":"Mecklenburg-Vorpommern","BL_ID":"13","county":"LK Nordwestmecklenburg","last_update":"14.02., 00:00","cases7_per_100k":95.2988027693453,"recovered":null,"EWZ_BL":1611160,"cases7_bl_per_100k":62.9360212517689,"cases7_bl":1014,"death7_bl":0,"cases7_lk":151,"death7_lk":0,"cases7_per_100k_txt":"95,3","AdmUnitId":13074}]}