{"data":[{"betten_frei":62,"betten_belegt":270,"betten_gesamt":332,"Anteil_betten_frei":18.6746987951807,"faelle_covid_aktuell":6,"faelle_covid_aktuell_beatmet":4,"Anteil_covid_beatmet":66,"Anteil_COVID_betten":2.531646,"daten_stand":"16.06.2022 10:19 Uhr","OBJECTID":362,"ADE":4,"GF":4,"BSG":1,"RS":"14713","AGS":"14713","SDV_RS":"147130000000","GEN":"Leipzig","BEZ":"Kreisfreie Stadt","IBZ":40,"BEM":"--","NBD":"ja","SN_L":"14","SN_R":"7","SN_K":"13","SN_V1":"00","SN_V2":"00","SN_G":"000","FK_S3":"K","NUTS":"DED51","RS_0":"147130000000","AGS_0":"14713000","WSK":"2008/08/01 00:00:00.000","EWZ":597493,"KFL":297.8,"DEBKG_ID":"DEBKGDL20000002S","Shape__Area":299199530.356689,"Shape__Length":121009.563030988,"death_rate":0.406293138051555,"cases":204286,"deaths":830,"cases_per_100k":34190.5260814771,"cases_per_population":34.1905260814771,"BL":"Sachsen","BL_ID":"14","county":"SK Leipzig","last_update":"17.06., 00:00","cases7_per_100k":407.536155235291,"recovered":null,"EWZ_BL":4056941,"cases7_bl_per_100k":245.307979583632,"cases7_bl":9952,"death7_bl":1,"cases7_lk":2435,"death7_lk":0,"cases7_per_100k_txt":"407,5","AdmUnitId":14713}]}