{"states":[{"name":"Baden-Württemberg","total":11100394,"rs":"08","vaccinated":6753762,"difference_to_the_previous_day":44456},{"name":"Bayern","total":13124737,"rs":"09","vaccinated":8052216,"difference_to_the_previous_day":48769},{"name":"Berlin","total":3669491,"rs":"11","vaccinated":2210760,"difference_to_the_previous_day":22995},{"name":"Brandenburg","total":2521893,"rs":"12","vaccinated":1457684,"difference_to_the_previous_day":14236},{"name":"Bremen","total":681202,"rs":"04","vaccinated":459824,"difference_to_the_previous_day":4436},{"name":"Hamburg","total":1847253,"rs":"02","vaccinated":1097419,"difference_to_the_previous_day":5073},{"name":"Hessen","total":6288080,"rs":"06","vaccinated":3779655,"difference_to_the_previous_day":29120},{"name":"Mecklenburg-Vorpommern","total":1608138,"rs":"13","vaccinated":1013259,"difference_to_the_previous_day":7441},{"name":"Niedersachsen","total":7993608,"rs":"03","vaccinated":4814244,"difference_to_the_previous_day":27728},{"name":"Nordrhein-Westfalen","total":17947221,"rs":"05","vaccinated":11635650,"difference_to_the_previous_day":93155},{"name":"Rheinland-Pfalz","total":4093903,"rs":"07","vaccinated":2518687,"difference_to_the_previous_day":22522},{"name":"Saarland","total":986887,"rs":"10","vaccinated":678542,"difference_to_the_previous_day":5402},{"name":"Sachsen","total":4071971,"rs":"14","vaccinated":2438361,"difference_to_the_previous_day":19465},{"name":"Sachsen-Anhalt","total":2194782,"rs":"15","vaccinated":1303242,"difference_to_the_previous_day":11248},{"name":"Schleswig-Holstein","total":2903773,"rs":"01","vaccinated":1861549,"difference_to_the_previous_day":23309},{"name":"Thüringen","total":2133378,"rs":"16","vaccinated":1311967,"difference_to_the_previous_day":13175}],"last_update":"01.06., 00:00","germany":{"total":83166711,"sum_vaccine_doses":51540953,"difference_to_the_previous_day":394790,"cumsum_7_days_ago":47488796}}