{"states":[{"name":"Baden-Württemberg","total":11100394,"rs":"08","vaccinated":10736731,"difference_to_the_previous_day":32902},{"name":"Bayern","total":13124737,"rs":"09","vaccinated":12500111,"difference_to_the_previous_day":52420},{"name":"Berlin","total":3669491,"rs":"11","vaccinated":3530825,"difference_to_the_previous_day":11552},{"name":"Brandenburg","total":2521893,"rs":"12","vaccinated":2282612,"difference_to_the_previous_day":5261},{"name":"Bremen","total":681202,"rs":"04","vaccinated":739417,"difference_to_the_previous_day":3558},{"name":"Hamburg","total":1847253,"rs":"02","vaccinated":1778273,"difference_to_the_previous_day":6916},{"name":"Hessen","total":6288080,"rs":"06","vaccinated":6042692,"difference_to_the_previous_day":28123},{"name":"Mecklenburg-Vorpommern","total":1608138,"rs":"13","vaccinated":1599213,"difference_to_the_previous_day":5046},{"name":"Niedersachsen","total":7993608,"rs":"03","vaccinated":7865688,"difference_to_the_previous_day":40303},{"name":"Nordrhein-Westfalen","total":17947221,"rs":"05","vaccinated":18776979,"difference_to_the_previous_day":85154},{"name":"Rheinland-Pfalz","total":4093903,"rs":"07","vaccinated":4026116,"difference_to_the_previous_day":15446},{"name":"Saarland","total":986887,"rs":"10","vaccinated":1057884,"difference_to_the_previous_day":5004},{"name":"Sachsen","total":4071971,"rs":"14","vaccinated":3566290,"difference_to_the_previous_day":12220},{"name":"Sachsen-Anhalt","total":2194782,"rs":"15","vaccinated":2043931,"difference_to_the_previous_day":7133},{"name":"Schleswig-Holstein","total":2903773,"rs":"01","vaccinated":2999734,"difference_to_the_previous_day":12637},{"name":"Thüringen","total":2133378,"rs":"16","vaccinated":1959999,"difference_to_the_previous_day":3962}],"last_update":"07.07., 00:00","germany":{"total":83166711,"sum_vaccine_doses":81782620,"difference_to_the_previous_day":327931,"cumsum_7_days_ago":75037194}}