{"locations":[{"OBJECTID":15,"LAN_ew_AGS":"01","LAN_ew_GEN":"Schleswig-Holstein","LAN_ew_BEZ":"Land","LAN_ew_EWZ":2910875,"Fallzahl":86264,"Death":1750,"cases7_bl_per_100k":93.8892944561343,"cases7_bl":2733,"death7_bl":4,"OBJECTID_1":1,"last_update":"11.11., 23:00","new_cases":492,"new_deaths":3},{"OBJECTID":5,"LAN_ew_AGS":"04","LAN_ew_GEN":"Bremen","LAN_ew_BEZ":"Freie Hansestadt","LAN_ew_EWZ":680130,"Fallzahl":36469,"Death":535,"cases7_bl_per_100k":100.569008865952,"cases7_bl":684,"death7_bl":0,"OBJECTID_1":4,"last_update":"11.11., 23:00","new_cases":151,"new_deaths":1},{"OBJECTID":9,"LAN_ew_AGS":"03","LAN_ew_GEN":"Niedersachsen","LAN_ew_BEZ":"Land","LAN_ew_EWZ":8003421,"Fallzahl":336331,"Death":6153,"cases7_bl_per_100k":113.651399820152,"cases7_bl":9096,"death7_bl":8,"OBJECTID_1":3,"last_update":"11.11., 23:00","new_cases":2143,"new_deaths":5},{"OBJECTID":6,"LAN_ew_AGS":"02","LAN_ew_GEN":"Hamburg","LAN_ew_BEZ":"Freie und Hansestadt","LAN_ew_EWZ":1852478,"Fallzahl":103336,"Death":1844,"cases7_bl_per_100k":136.519839911729,"cases7_bl":2529,"death7_bl":0,"OBJECTID_1":2,"last_update":"11.11., 23:00","new_cases":516,"new_deaths":1},{"OBJECTID":12,"LAN_ew_AGS":"10","LAN_ew_GEN":"Saarland","LAN_ew_BEZ":"Land","LAN_ew_EWZ":983991,"Fallzahl":52085,"Death":1081,"cases7_bl_per_100k":153.863195903215,"cases7_bl":1514,"death7_bl":1,"OBJECTID_1":10,"last_update":"11.11., 23:00","new_cases":300,"new_deaths":3},{"OBJECTID":10,"LAN_ew_AGS":"05","LAN_ew_GEN":"Nordrhein-Westfalen","LAN_ew_BEZ":"Land","LAN_ew_EWZ":17925570,"Fallzahl":1057847,"Death":18445,"cases7_bl_per_100k":157.032663396478,"cases7_bl":28149,"death7_bl":16,"OBJECTID_1":5,"last_update":"11.11., 23:00","new_cases":5865,"new_deaths":21},{"OBJECTID":11,"LAN_ew_AGS":"07","LAN_ew_GEN":"Rheinland-Pfalz","LAN_ew_BEZ":"Land","LAN_ew_EWZ":4098391,"Fallzahl":203954,"Death":4158,"cases7_bl_per_100k":161.624403332918,"cases7_bl":6624,"death7_bl":6,"OBJECTID_1":7,"last_update":"11.11., 23:00","new_cases":1451,"new_deaths":13},{"OBJECTID":8,"LAN_ew_AGS":"13","LAN_ew_GEN":"Mecklenburg-Vorpommern","LAN_ew_BEZ":"Land","LAN_ew_EWZ":1610774,"Fallzahl":57564,"Death":1273,"cases7_bl_per_100k":165.634657624223,"cases7_bl":2668,"death7_bl":2,"OBJECTID_1":13,"last_update":"11.11., 23:00","new_cases":462,"new_deaths":2},{"OBJECTID":7,"LAN_ew_AGS":"06","LAN_ew_GEN":"Hessen","LAN_ew_BEZ":"Land","LAN_ew_EWZ":6293154,"Fallzahl":373022,"Death":7962,"cases7_bl_per_100k":171.599169510233,"cases7_bl":10799,"death7_bl":16,"OBJECTID_1":6,"last_update":"11.11., 23:00","new_cases":2144,"new_deaths":17},{"OBJECTID":14,"LAN_ew_AGS":"15","LAN_ew_GEN":"Sachsen-Anhalt","LAN_ew_BEZ":"Land","LAN_ew_EWZ":2180684,"Fallzahl":121540,"Death":3629,"cases7_bl_per_100k":269.319167747367,"cases7_bl":5873,"death7_bl":7,"OBJECTID_1":15,"last_update":"11.11., 23:00","new_cases":1597,"new_deaths":5},{"OBJECTID":3,"LAN_ew_AGS":"11","LAN_ew_GEN":"Berlin","LAN_ew_BEZ":"Land","LAN_ew_EWZ":3664088,"Fallzahl":240189,"Death":3756,"cases7_bl_per_100k":279.196351179338,"cases7_bl":10230,"death7_bl":3,"OBJECTID_1":11,"last_update":"11.11., 23:00","new_cases":2184,"new_deaths":3},{"OBJECTID":4,"LAN_ew_AGS":"12","LAN_ew_GEN":"Brandenburg","LAN_ew_BEZ":"Land","LAN_ew_EWZ":2531071,"Fallzahl":137171,"Death":3968,"cases7_bl_per_100k":323.815491544884,"cases7_bl":8196,"death7_bl":2,"OBJECTID_1":12,"last_update":"11.11., 23:00","new_cases":2125,"new_deaths":7},{"OBJECTID":1,"LAN_ew_AGS":"08","LAN_ew_GEN":"Baden-Württemberg","LAN_ew_BEZ":"Land","LAN_ew_EWZ":11103043,"Fallzahl":689512,"Death":11203,"cases7_bl_per_100k":332.296290305279,"cases7_bl":36895,"death7_bl":15,"OBJECTID_1":8,"last_update":"11.11., 23:00","new_cases":7978,"new_deaths":24},{"OBJECTID":2,"LAN_ew_AGS":"09","LAN_ew_GEN":"Bayern","LAN_ew_BEZ":"Freistaat","LAN_ew_EWZ":13140183,"Fallzahl":911465,"Death":16497,"cases7_bl_per_100k":454.940391621639,"cases7_bl":59780,"death7_bl":51,"OBJECTID_1":9,"last_update":"11.11., 23:00","new_cases":13197,"new_deaths":63},{"OBJECTID":16,"LAN_ew_AGS":"16","LAN_ew_GEN":"Thüringen","LAN_ew_BEZ":"Freistaat","LAN_ew_EWZ":2120237,"Fallzahl":169784,"Death":4651,"cases7_bl_per_100k":491.312999442987,"cases7_bl":10417,"death7_bl":20,"OBJECTID_1":16,"last_update":"11.11., 23:00","new_cases":2298,"new_deaths":12},{"OBJECTID":13,"LAN_ew_AGS":"14","LAN_ew_GEN":"Sachsen","LAN_ew_BEZ":"Freistaat","LAN_ew_EWZ":4056941,"Fallzahl":366357,"Death":10484,"cases7_bl_per_100k":569.024789860143,"cases7_bl":23085,"death7_bl":13,"OBJECTID_1":14,"last_update":"11.11., 23:00","new_cases":5737,"new_deaths":11}],"last_update":"11.11., 23:00"}