{"locations":[{"OBJECTID":16,"AdmUnitId":16,"LAN_ew_AGS":"16","LAN_ew_GEN":"Thüringen","LAN_ew_BEZ":"Freistaat","LAN_ew_EWZ":2108863,"Fallzahl":880548,"Death":8259,"cases7_bl_per_100k":45.3799037680494,"cases7_bl":957,"death7_bl":1,"OBJECTID_1":16,"last_update":"19.02., 23:00","new_cases":0,"new_deaths":0},{"OBJECTID":6,"AdmUnitId":2,"LAN_ew_AGS":"02","LAN_ew_GEN":"Hamburg","LAN_ew_BEZ":"Freie und Hansestadt","LAN_ew_EWZ":1853935,"Fallzahl":804589,"Death":3593,"cases7_bl_per_100k":46.2799396958362,"cases7_bl":858,"death7_bl":2,"OBJECTID_1":2,"last_update":"19.02., 23:00","new_cases":0,"new_deaths":0},{"OBJECTID":13,"AdmUnitId":14,"LAN_ew_AGS":"14","LAN_ew_GEN":"Sachsen","LAN_ew_BEZ":"Freistaat","LAN_ew_EWZ":4043002,"Fallzahl":1949531,"Death":16777,"cases7_bl_per_100k":47.9594123376639,"cases7_bl":1939,"death7_bl":0,"OBJECTID_1":14,"last_update":"19.02., 23:00","new_cases":0,"new_deaths":0},{"OBJECTID":8,"AdmUnitId":13,"LAN_ew_AGS":"13","LAN_ew_GEN":"Mecklenburg-Vorpommern","LAN_ew_BEZ":"Land","LAN_ew_EWZ":1611160,"Fallzahl":709135,"Death":2752,"cases7_bl_per_100k":56.7293130415353,"cases7_bl":914,"death7_bl":1,"OBJECTID_1":13,"last_update":"19.02., 23:00","new_cases":0,"new_deaths":0},{"OBJECTID":15,"AdmUnitId":1,"LAN_ew_AGS":"01","LAN_ew_GEN":"Schleswig-Holstein","LAN_ew_BEZ":"Land","LAN_ew_EWZ":2922005,"Fallzahl":1171190,"Death":3459,"cases7_bl_per_100k":59.6508219527345,"cases7_bl":1743,"death7_bl":2,"OBJECTID_1":1,"last_update":"19.02., 23:00","new_cases":0,"new_deaths":0},{"OBJECTID":14,"AdmUnitId":15,"LAN_ew_AGS":"15","LAN_ew_GEN":"Sachsen-Anhalt","LAN_ew_BEZ":"Land","LAN_ew_EWZ":2169253,"Fallzahl":957079,"Death":6256,"cases7_bl_per_100k":66.1979031491486,"cases7_bl":1436,"death7_bl":2,"OBJECTID_1":15,"last_update":"19.02., 23:00","new_cases":0,"new_deaths":0},{"OBJECTID":3,"AdmUnitId":11,"LAN_ew_AGS":"11","LAN_ew_GEN":"Berlin","LAN_ew_BEZ":"Land","LAN_ew_EWZ":3677472,"Fallzahl":1424093,"Death":5508,"cases7_bl_per_100k":68.5525273883798,"cases7_bl":2521,"death7_bl":1,"OBJECTID_1":11,"last_update":"19.02., 23:00","new_cases":0,"new_deaths":0},{"OBJECTID":1,"AdmUnitId":8,"LAN_ew_AGS":"08","LAN_ew_GEN":"Baden-Württemberg","LAN_ew_BEZ":"Land","LAN_ew_EWZ":11124642,"Fallzahl":5032817,"Death":19103,"cases7_bl_per_100k":91.4905845958908,"cases7_bl":10178,"death7_bl":6,"OBJECTID_1":8,"last_update":"19.02., 23:00","new_cases":0,"new_deaths":0},{"OBJECTID":5,"AdmUnitId":4,"LAN_ew_AGS":"04","LAN_ew_GEN":"Bremen","LAN_ew_BEZ":"Freie Hansestadt","LAN_ew_EWZ":676463,"Fallzahl":301994,"Death":961,"cases7_bl_per_100k":95.4967233980277,"cases7_bl":646,"death7_bl":0,"OBJECTID_1":4,"last_update":"19.02., 23:00","new_cases":0,"new_deaths":0},{"OBJECTID":4,"AdmUnitId":12,"LAN_ew_AGS":"12","LAN_ew_GEN":"Brandenburg","LAN_ew_BEZ":"Land","LAN_ew_EWZ":2537868,"Fallzahl":1109110,"Death":6463,"cases7_bl_per_100k":98.5078814185765,"cases7_bl":2500,"death7_bl":1,"OBJECTID_1":12,"last_update":"19.02., 23:00","new_cases":0,"new_deaths":0},{"OBJECTID":9,"AdmUnitId":3,"LAN_ew_AGS":"03","LAN_ew_GEN":"Niedersachsen","LAN_ew_BEZ":"Land","LAN_ew_EWZ":8027031,"Fallzahl":3839209,"Death":13454,"cases7_bl_per_100k":108.495905895966,"cases7_bl":8709,"death7_bl":9,"OBJECTID_1":3,"last_update":"19.02., 23:00","new_cases":0,"new_deaths":0},{"OBJECTID":11,"AdmUnitId":7,"LAN_ew_AGS":"07","LAN_ew_GEN":"Rheinland-Pfalz","LAN_ew_BEZ":"Land","LAN_ew_EWZ":4106485,"Fallzahl":1753320,"Death":6907,"cases7_bl_per_100k":118.83642579968,"cases7_bl":4880,"death7_bl":6,"OBJECTID_1":7,"last_update":"19.02., 23:00","new_cases":0,"new_deaths":0},{"OBJECTID":2,"AdmUnitId":9,"LAN_ew_AGS":"09","LAN_ew_GEN":"Bayern","LAN_ew_BEZ":"Freistaat","LAN_ew_EWZ":13176989,"Fallzahl":6704634,"Death":28323,"cases7_bl_per_100k":122.615265141376,"cases7_bl":16157,"death7_bl":16,"OBJECTID_1":9,"last_update":"19.02., 23:00","new_cases":0,"new_deaths":0},{"OBJECTID":10,"AdmUnitId":5,"LAN_ew_AGS":"05","LAN_ew_GEN":"Nordrhein-Westfalen","LAN_ew_BEZ":"Land","LAN_ew_EWZ":17924591,"Fallzahl":7972467,"Death":31089,"cases7_bl_per_100k":126.641662283954,"cases7_bl":22700,"death7_bl":7,"OBJECTID_1":5,"last_update":"19.02., 23:00","new_cases":0,"new_deaths":0},{"OBJECTID":7,"AdmUnitId":6,"LAN_ew_AGS":"06","LAN_ew_GEN":"Hessen","LAN_ew_BEZ":"Land","LAN_ew_EWZ":6295017,"Fallzahl":2905263,"Death":12274,"cases7_bl_per_100k":136.234739318416,"cases7_bl":8576,"death7_bl":5,"OBJECTID_1":6,"last_update":"19.02., 23:00","new_cases":0,"new_deaths":0},{"OBJECTID":12,"AdmUnitId":10,"LAN_ew_AGS":"10","LAN_ew_GEN":"Saarland","LAN_ew_BEZ":"Land","LAN_ew_EWZ":982348,"Fallzahl":487632,"Death":2111,"cases7_bl_per_100k":148.521705139116,"cases7_bl":1459,"death7_bl":0,"OBJECTID_1":10,"last_update":"19.02., 23:00","new_cases":0,"new_deaths":0}],"last_update":"19.02., 23:00"}