{"lowest5":[{"cases_per_100k":7742.01316423182,"RS":"11010","EWZ":274076,"cases7_per_100k":63.5,"GEN":"Berlin Marzahn-Hellersdorf","BEZ":"Bezirk","newCases":null},{"cases_per_100k":18280.3395619851,"RS":"16075","EWZ":79632,"cases7_per_100k":108,"GEN":"Saale-Orla-Kreis","BEZ":"Landkreis","newCases":10},{"cases_per_100k":17861.6506556342,"RS":"16072","EWZ":57044,"cases7_per_100k":129.7,"GEN":"Sonneberg","BEZ":"Landkreis","newCases":8},{"cases_per_100k":14963.9322261366,"RS":"14511","EWZ":244401,"cases7_per_100k":130.1,"GEN":"Chemnitz","BEZ":"Kreisfreie Stadt","newCases":66},{"cases_per_100k":17439.9857082245,"RS":"14523","EWZ":223905,"cases7_per_100k":140.2,"GEN":"Vogtlandkreis","BEZ":"Landkreis","newCases":47}],"highest5":[{"cases_per_100k":12983.4174993732,"RS":"11002","EWZ":279210,"cases7_per_100k":1586.6,"GEN":"Berlin Friedrichshain-Kreuzberg","BEZ":"Bezirk","newCases":917},{"cases_per_100k":14222.8320078867,"RS":"11008","EWZ":318509,"cases7_per_100k":1488.5,"GEN":"Berlin Neukölln","BEZ":"Bezirk","newCases":1025},{"cases_per_100k":9590.29110105847,"RS":"04011","EWZ":566573,"cases7_per_100k":1481,"GEN":"Bremen","BEZ":"Kreisfreie Stadt","newCases":1500},{"cases_per_100k":12769.4677519682,"RS":"11001","EWZ":374581,"cases7_per_100k":1332.4,"GEN":"Berlin Mitte","BEZ":"Bezirk","newCases":1162},{"cases_per_100k":11941.7064531033,"RS":"11012","EWZ":259720,"cases7_per_100k":1161.6,"GEN":"Berlin Reinickendorf","BEZ":"Bezirk","newCases":512}],"highest5EWZ":[{"cases_per_100k":9130.95864026455,"RS":"02000","EWZ":1852478,"cases7_per_100k":737.7,"GEN":"Hamburg","BEZ":"Kreisfreie Stadt","newCases":3840},{"cases_per_100k":10937.493700452,"RS":"09162","EWZ":1488202,"cases7_per_100k":761.9,"GEN":"München","BEZ":"Kreisfreie Stadt","newCases":2135},{"cases_per_100k":7437.87489288775,"RS":"03241","EWZ":1155330,"cases7_per_100k":402.9,"GEN":"Region Hannover","BEZ":"Landkreis","newCases":1021},{"cases_per_100k":9987.37422680983,"RS":"05315","EWZ":1083498,"cases7_per_100k":332.3,"GEN":"Köln","BEZ":"Kreisfreie Stadt","newCases":1099},{"cases_per_100k":10721.3154230314,"RS":"06412","EWZ":764104,"cases7_per_100k":939,"GEN":"Frankfurt am Main","BEZ":"Kreisfreie Stadt","newCases":1462},{"cases_per_100k":10101.7761242573,"RS":"08111","EWZ":630305,"cases7_per_100k":523.2,"GEN":"Stuttgart","BEZ":"Stadtkreis","newCases":578},{"cases_per_100k":8958.41088887922,"RS":"05111","EWZ":620523,"cases7_per_100k":578.5,"GEN":"Düsseldorf","BEZ":"Kreisfreie Stadt","newCases":328},{"cases_per_100k":8286.68234465832,"RS":"05562","EWZ":613599,"cases7_per_100k":252.9,"GEN":"Recklinghausen","BEZ":"Kreis","newCases":232},{"cases_per_100k":7725.50489277535,"RS":"05382","EWZ":600375,"cases7_per_100k":457.4,"GEN":"Rhein-Sieg-Kreis","BEZ":"Kreis","newCases":529},{"cases_per_100k":9611.66072238503,"RS":"14713","EWZ":597493,"cases7_per_100k":341.9,"GEN":"Leipzig","BEZ":"Kreisfreie Stadt","newCases":415},{"cases_per_100k":9141.6310473442,"RS":"05913","EWZ":587696,"cases7_per_100k":657,"GEN":"Dortmund","BEZ":"Kreisfreie Stadt","newCases":610},{"cases_per_100k":8532.91896671617,"RS":"05113","EWZ":582415,"cases7_per_100k":599.2,"GEN":"Essen","BEZ":"Kreisfreie Stadt","newCases":806},{"cases_per_100k":8912.18778688215,"RS":"05334","EWZ":556631,"cases7_per_100k":575.1,"GEN":"Städteregion Aachen","BEZ":"Kreis","newCases":907},{"cases_per_100k":15570.9809124692,"RS":"14612","EWZ":556227,"cases7_per_100k":298.1,"GEN":"Dresden","BEZ":"Kreisfreie Stadt","newCases":366},{"cases_per_100k":8393.14670951949,"RS":"08226","EWZ":548233,"cases7_per_100k":452.4,"GEN":"Rhein-Neckar-Kreis","BEZ":"Landkreis","newCases":326},{"cases_per_100k":9858.8732244468,"RS":"08118","EWZ":544971,"cases7_per_100k":478,"GEN":"Ludwigsburg","BEZ":"Landkreis","newCases":402},{"cases_per_100k":10256.232466357,"RS":"08116","EWZ":533617,"cases7_per_100k":496.8,"GEN":"Esslingen","BEZ":"Landkreis","newCases":682},{"cases_per_100k":12652.0969152913,"RS":"09564","EWZ":515543,"cases7_per_100k":491.9,"GEN":"Nürnberg","BEZ":"Kreisfreie Stadt","newCases":316},{"cases_per_100k":9737.33829416095,"RS":"05112","EWZ":495885,"cases7_per_100k":575.3,"GEN":"Duisburg","BEZ":"Kreisfreie Stadt","newCases":714},{"cases_per_100k":9384.4590995247,"RS":"05158","EWZ":484322,"cases7_per_100k":584.5,"GEN":"Mettmann","BEZ":"Kreis","newCases":484}],"highest5casesPer100k":[{"cases_per_100k":22012.3241882626,"RS":"14628","EWZ":244722,"cases7_per_100k":267.7,"GEN":"Sächsische Schweiz-Osterzgebirge","BEZ":"Landkreis","newCases":92},{"cases_per_100k":21118.4188450052,"RS":"14625","EWZ":298010,"cases7_per_100k":179.2,"GEN":"Bautzen","BEZ":"Landkreis","newCases":107},{"cases_per_100k":20640.7023442608,"RS":"14521","EWZ":331917,"cases7_per_100k":144.9,"GEN":"Erzgebirgskreis","BEZ":"Landkreis","newCases":71},{"cases_per_100k":20314.0960163432,"RS":"16069","EWZ":62656,"cases7_per_100k":213.9,"GEN":"Hildburghausen","BEZ":"Landkreis","newCases":14},{"cases_per_100k":19182.0144692995,"RS":"14627","EWZ":240371,"cases7_per_100k":255,"GEN":"Meißen","BEZ":"Landkreis","newCases":72}]}