{"lowest5":[{"cases_per_100k":7602.91639119868,"RS":"07137","EWZ":214786,"cases7_per_100k":218.8,"GEN":"Mayen-Koblenz","BEZ":"Landkreis","newCases":283},{"cases_per_100k":17407.0012827409,"RS":"16076","EWZ":96668,"cases7_per_100k":257.6,"GEN":"Greiz","BEZ":"Landkreis","newCases":19},{"cases_per_100k":21153.4811413697,"RS":"14521","EWZ":331917,"cases7_per_100k":285.6,"GEN":"Erzgebirgskreis","BEZ":"Landkreis","newCases":96},{"cases_per_100k":9286.69700497407,"RS":"07111","EWZ":113388,"cases7_per_100k":310.4,"GEN":"Koblenz","BEZ":"Kreisfreie Stadt","newCases":178},{"cases_per_100k":17110.016741891,"RS":"16073","EWZ":102139,"cases7_per_100k":329,"GEN":"Saalfeld-Rudolstadt","BEZ":"Landkreis","newCases":10}],"highest5":[{"cases_per_100k":12392.2114047288,"RS":"09188","EWZ":136610,"cases7_per_100k":2847.5,"GEN":"Starnberg","BEZ":"Landkreis","newCases":351},{"cases_per_100k":14097.5286057606,"RS":"05120","EWZ":111516,"cases7_per_100k":2718,"GEN":"Remscheid","BEZ":"Kreisfreie Stadt","newCases":653},{"cases_per_100k":15297.2786085978,"RS":"11007","EWZ":341296,"cases7_per_100k":2636.7,"GEN":"Berlin Tempelhof-Schöneberg","BEZ":"Bezirk","newCases":1050},{"cases_per_100k":15982.7742929531,"RS":"09174","EWZ":155117,"cases7_per_100k":2630.3,"GEN":"Dachau","BEZ":"Landkreis","newCases":553},{"cases_per_100k":19641.2032313059,"RS":"11008","EWZ":318509,"cases7_per_100k":2571.4,"GEN":"Berlin Neukölln","BEZ":"Bezirk","newCases":1524}],"highest5EWZ":[{"cases_per_100k":13653.549461856,"RS":"02000","EWZ":1852478,"cases7_per_100k":1598.4,"GEN":"Hamburg","BEZ":"Kreisfreie Stadt","newCases":3054},{"cases_per_100k":14886.0168176094,"RS":"09162","EWZ":1488202,"cases7_per_100k":1678.8,"GEN":"München","BEZ":"Kreisfreie Stadt","newCases":6829},{"cases_per_100k":9857.44332788035,"RS":"03241","EWZ":1155330,"cases7_per_100k":1293.8,"GEN":"Region Hannover","BEZ":"Landkreis","newCases":1402},{"cases_per_100k":13277.8279240017,"RS":"05315","EWZ":1083498,"cases7_per_100k":838.2,"GEN":"Köln","BEZ":"Kreisfreie Stadt","newCases":2323},{"cases_per_100k":14780.3178624899,"RS":"06412","EWZ":764104,"cases7_per_100k":2246.4,"GEN":"Frankfurt am Main","BEZ":"Kreisfreie Stadt","newCases":2977},{"cases_per_100k":11772.0785968698,"RS":"08111","EWZ":630305,"cases7_per_100k":690.9,"GEN":"Stuttgart","BEZ":"Stadtkreis","newCases":481},{"cases_per_100k":13234.8035447518,"RS":"05111","EWZ":620523,"cases7_per_100k":1706,"GEN":"Düsseldorf","BEZ":"Kreisfreie Stadt","newCases":4442},{"cases_per_100k":9448.3530774985,"RS":"05562","EWZ":613599,"cases7_per_100k":642.6,"GEN":"Recklinghausen","BEZ":"Kreis","newCases":1007},{"cases_per_100k":9967.43701853009,"RS":"05382","EWZ":600375,"cases7_per_100k":716.9,"GEN":"Rhein-Sieg-Kreis","BEZ":"Kreis","newCases":1018},{"cases_per_100k":11610.6799577568,"RS":"14713","EWZ":597493,"cases7_per_100k":1034.7,"GEN":"Leipzig","BEZ":"Kreisfreie Stadt","newCases":477},{"cases_per_100k":12593.75595546,"RS":"05913","EWZ":587696,"cases7_per_100k":1923.4,"GEN":"Dortmund","BEZ":"Kreisfreie Stadt","newCases":1707},{"cases_per_100k":10873.3463252148,"RS":"05113","EWZ":582415,"cases7_per_100k":1159.7,"GEN":"Essen","BEZ":"Kreisfreie Stadt","newCases":476},{"cases_per_100k":12920.3121221802,"RS":"04011","EWZ":566573,"cases7_per_100k":1401.1,"GEN":"Bremen","BEZ":"Kreisfreie Stadt","newCases":1219},{"cases_per_100k":12605.6579673069,"RS":"05334","EWZ":556631,"cases7_per_100k":1717.7,"GEN":"Städteregion Aachen","BEZ":"Kreis","newCases":638},{"cases_per_100k":17485.6668230776,"RS":"14612","EWZ":556227,"cases7_per_100k":905.6,"GEN":"Dresden","BEZ":"Kreisfreie Stadt","newCases":650},{"cases_per_100k":9838.33516041537,"RS":"08226","EWZ":548233,"cases7_per_100k":811.9,"GEN":"Rhein-Neckar-Kreis","BEZ":"Landkreis","newCases":759},{"cases_per_100k":12085.4137192621,"RS":"08118","EWZ":544971,"cases7_per_100k":919.7,"GEN":"Ludwigsburg","BEZ":"Landkreis","newCases":599},{"cases_per_100k":12616.3521776855,"RS":"08116","EWZ":533617,"cases7_per_100k":1133.4,"GEN":"Esslingen","BEZ":"Landkreis","newCases":1273},{"cases_per_100k":16016.5107469212,"RS":"09564","EWZ":515543,"cases7_per_100k":1788.4,"GEN":"Nürnberg","BEZ":"Kreisfreie Stadt","newCases":374},{"cases_per_100k":12719.6829910161,"RS":"05112","EWZ":495885,"cases7_per_100k":1532,"GEN":"Duisburg","BEZ":"Kreisfreie Stadt","newCases":1332}],"highest5casesPer100k":[{"cases_per_100k":22966.8767009096,"RS":"14628","EWZ":244722,"cases7_per_100k":546.3,"GEN":"Sächsische Schweiz-Osterzgebirge","BEZ":"Landkreis","newCases":47},{"cases_per_100k":22051.6090064092,"RS":"14625","EWZ":298010,"cases7_per_100k":469.8,"GEN":"Bautzen","BEZ":"Landkreis","newCases":73},{"cases_per_100k":21097.740040858,"RS":"16069","EWZ":62656,"cases7_per_100k":411.8,"GEN":"Hildburghausen","BEZ":"Landkreis","newCases":81},{"cases_per_100k":20342.7202116728,"RS":"14627","EWZ":240371,"cases7_per_100k":687.3,"GEN":"Meißen","BEZ":"Landkreis","newCases":163},{"cases_per_100k":19795.7369458063,"RS":"14522","EWZ":301474,"cases7_per_100k":480.3,"GEN":"Mittelsachsen","BEZ":"Landkreis","newCases":99}]}