{"states":[{"name":"Baden-Württemberg","total":11100394,"rs":"08","vaccinated":14841341,"difference_to_the_previous_day":6746},{"name":"Bayern","total":13124737,"rs":"09","vaccinated":17696086,"difference_to_the_previous_day":9224},{"name":"Berlin","total":3669491,"rs":"11","vaccinated":5199237,"difference_to_the_previous_day":4353},{"name":"Brandenburg","total":2521893,"rs":"12","vaccinated":3159114,"difference_to_the_previous_day":812},{"name":"Bremen","total":681202,"rs":"04","vaccinated":1084596,"difference_to_the_previous_day":716},{"name":"Hamburg","total":1847253,"rs":"02","vaccinated":2740013,"difference_to_the_previous_day":960},{"name":"Hessen","total":6288080,"rs":"06","vaccinated":8637563,"difference_to_the_previous_day":3929},{"name":"Mecklenburg-Vorpommern","total":1608138,"rs":"13","vaccinated":2171997,"difference_to_the_previous_day":1076},{"name":"Niedersachsen","total":7993608,"rs":"03","vaccinated":11253751,"difference_to_the_previous_day":3403},{"name":"Nordrhein-Westfalen","total":17947221,"rs":"05","vaccinated":25977663,"difference_to_the_previous_day":4646},{"name":"Rheinland-Pfalz","total":4093903,"rs":"07","vaccinated":5690249,"difference_to_the_previous_day":2893},{"name":"Saarland","total":986887,"rs":"10","vaccinated":1475398,"difference_to_the_previous_day":757},{"name":"Sachsen","total":4071971,"rs":"14","vaccinated":4804048,"difference_to_the_previous_day":3351},{"name":"Sachsen-Anhalt","total":2194782,"rs":"15","vaccinated":2832745,"difference_to_the_previous_day":1925},{"name":"Schleswig-Holstein","total":2903773,"rs":"01","vaccinated":4254660,"difference_to_the_previous_day":873},{"name":"Thüringen","total":2133378,"rs":"16","vaccinated":2668568,"difference_to_the_previous_day":1767}],"last_update":"14.12., 00:00","germany":{"total":83166711,"sum_vaccine_doses":135403785,"difference_to_the_previous_day":47480,"cumsum_7_days_ago":128874193}}